{"doc": {"cmplid": "620684", "odino": "10183580", "mfr_name": "GENERAL MOTORS CORP.", "maketxt": "BUICK", "modeltxt": "RENDEZVOUS", "yeartxt": "2003", "crash": "N", "faildate": "2006-03-07", "fire": "N", "injured": "0", "deaths": "0", "compdesc": "ENGINE AND ENGINE COOLING", "city": "MAYFIELD", "state": "KY", "datea": "2007-02-26", "ldate": "2007-02-26", "occurrences": "2", "cdescr": "HAD TO REPLACE LEAKING INTAKE GASKET @ 56,000 MILES ON 2003 BUICK RENDEZVOUS. BUICK CUSTOMER SERVICES SAID THIS FAILURE WAS TO BE EXPECTED ON A VEHICLE WITH 50,000 MILES. TRADED RDV ONE YEAR LATER WHEN HEAD GASKET FAILED. *JB", "cmpl_type": "NHTSA WEB SITE", "police_rpt_yn": "N", "purch_dt": "2003-12-15", "orig_owner_yn": "Y", "anti_brakes_yn": "Y", "cruise_cont_yn": "Y", "num_cyls": "6", "drive_train": "FWD", "fuel_sys": "FI", "fuel_type": "GAS", "trans_type": "AUTO", "dealer_name": "BRANDON MOTOR", "dealer_city": "MURRAY", "dealer_state": "KY", "prod_type": "VEHICLE"}}